bme68x.cpython-37m-arm-linux-gnueabihf.so
bme68xConstants.py
bsecConstants.py
bme68x-1.0.2.data/headers/bme68x.h
bme68x-1.0.2.data/headers/bme68x_defs.h
bme68x-1.0.2.data/headers/internal_functions.h
bme68x-1.0.2.dist-info/METADATA
bme68x-1.0.2.dist-info/WHEEL
bme68x-1.0.2.dist-info/top_level.txt
bme68x-1.0.2.dist-info/RECORD
