Metadata-Version: 2.1
Name: bme68x
Version: 1.0.2
Summary: Python interface for BME68X sensor and BSEC
Home-page: https://github.com/pi3g/bme68x-python-library
Author: Nathan
Author-email: nathan@pi3g.com
License: MIT
Keywords: bme68x bme680 bme688 BME68X BME680 BME688 bsec BSEC sensor environment temperature pressure humidity air pollution
Platform: UNKNOWN
Classifier: Development Status :: 3 - Alpha
Classifier: Intended Audience :: Developers
Classifier: License :: OSI Approved :: MIT License
Classifier: Natural Language :: English
Classifier: Operating System :: POSIX :: Linux
Classifier: Programming Language :: Python :: Implementation :: CPython
Classifier: Topic :: Scientific/Engineering :: Atmospheric Science
